kev/__init__.py
kev/backends/__init__.py
kev/backends/redis/__init__.py
kev/backends/redis/db.py
kev/backends/s3/__init__.py
kev/backends/s3/db.py
kev/backends/s3redis/__init__.py
kev/backends/s3redis/db.py
kev/document.py
kev/exceptions.py
kev/loading.py
kev/properties.py
kev/query.py
kev/testcase.py
kev/tests/__init__.py
kev/tests/documents.py
kev/tests/properties.py
kev/tests/utils.py
kev/utils.py
kev-0.10.0.dist-info/LICENSE
kev-0.10.0.dist-info/WHEEL
kev-0.10.0.dist-info/METADATA
kev-0.10.0.dist-info/RECORD
