Metadata-Version: 2.1
Name: kev
Version: 0.10.0
Summary: K.E.V. (Keys, Extra Stuff, and Values) is a Python ORM for key-value stores and document databases based on Valley. Currently supported backends are Redis, S3 and a S3/Redis hybrid backend.
License: Apache-2.0
Author: Brian Jinwright
Author-email: brian@ipoots.com
Requires-Python: >=3.7,<4.0
Classifier: License :: OSI Approved :: Apache Software License
Classifier: Programming Language :: Python :: 3
Classifier: Programming Language :: Python :: 3.7
Classifier: Programming Language :: Python :: 3.8
Requires-Dist: boto3 (>=1.16.43,<2.0.0)
Requires-Dist: envs (>=1.3,<2.0)
Requires-Dist: jupyterlab (>=3.0.0,<4.0.0)
Requires-Dist: pyzmq (==19.0.2)
Requires-Dist: redis (>=3.5.3,<4.0.0)
Requires-Dist: valley (>=1.5.5,<2.0.0)
